{"swagger":"2.0","info":{"version":"v1","title":"My API"},"paths":{"/api/SampleData/WeatherForecasts":{"get":{"tags":["SampleData"],"operationId":"WeatherForecasts","consumes":[],"produces":["text/plain","application/json","text/json"],"parameters":[],"responses":{"200":{"description":"Success","schema":{"uniqueItems":false,"type":"array","items":{"$ref":"#/definitions/WeatherForecast"}}}}}}},"definitions":{"WeatherForecast":{"type":"object","properties":{"dateFormatted":{"type":"string"},"temperatureC":{"format":"int32","type":"integer"},"summary":{"type":"string"},"temperatureF":{"format":"int32","type":"integer","readOnly":true}}}}}